gpt_commit_msg.py
gpt_commit_msg-0.1.2.dist-info/LICENSE
gpt_commit_msg-0.1.2.dist-info/METADATA
gpt_commit_msg-0.1.2.dist-info/WHEEL
gpt_commit_msg-0.1.2.dist-info/entry_points.txt
gpt_commit_msg-0.1.2.dist-info/top_level.txt
gpt_commit_msg-0.1.2.dist-info/RECORD
