Metadata-Version: 2.1
Name: gpt-commit-msg
Version: 0.1.2
Summary: A package for generating commit messages using GPT
Home-page: https://github.com/rtwfroody/gpt-commit-msg
Author: Tim Newsome
Author-email: tim@casualhacker.net
License: UNKNOWN
Platform: UNKNOWN
Classifier: Development Status :: 3 - Alpha
Classifier: Intended Audience :: Developers
Classifier: License :: OSI Approved :: MIT License
Classifier: Programming Language :: Python :: 3
Classifier: Programming Language :: Python :: 3.6
Classifier: Programming Language :: Python :: 3.7
Classifier: Programming Language :: Python :: 3.8
Classifier: Programming Language :: Python :: 3.9
Requires-Python: >=3.6
License-File: LICENSE
Requires-Dist: openai
Requires-Dist: tiktoken
